cli.py
key_rotator.py
key_rotator_test.py
aws_key_rotator_project-1.0.0.dist-info/METADATA
aws_key_rotator_project-1.0.0.dist-info/WHEEL
aws_key_rotator_project-1.0.0.dist-info/entry_points.txt
aws_key_rotator_project-1.0.0.dist-info/top_level.txt
aws_key_rotator_project-1.0.0.dist-info/RECORD
